LICENSE
MANIFEST.in
README.md
requirements.txt
setup.py
bgzip/__init__.py
bgzip/version.py
bgzip.egg-info/PKG-INFO
bgzip.egg-info/SOURCES.txt
bgzip.egg-info/dependency_links.txt
bgzip.egg-info/not-zip-safe
bgzip.egg-info/top_level.txt
bgzip_utils/bgzip_utils.c
bgzip_utils/bgzip_utils.pyx
bgzip_utils/cpython_nogil.pxd
bgzip_utils/czlib.pxd
tests/test_bgzip.py