Metadata-Version: 2.4
Name: bgzip
Version: 0.5.1
Summary: Utilities working with blocked gzip streams.
Home-page: https://github.com/DataBiosphere/bgzip.git
Author: Brian Hannafious
Author-email: bhannafi@ucsc.edu
License: MIT
Platform: Posix
Platform: MacOS X
Classifier: Intended Audience :: Developers
Classifier: License :: OSI Approved :: MIT License
Classifier: Programming Language :: Python :: 3.7
License-File: LICENSE
Dynamic: author
Dynamic: author-email
Dynamic: classifier
Dynamic: description
Dynamic: description-content-type
Dynamic: home-page
Dynamic: license
Dynamic: license-file
Dynamic: platform
Dynamic: summary
